bunnyapi/__init__.py
bunnyapi/collections.py
bunnyapi/storage.py
bunnyapi/videos.py
bunnyapi-0.1.5.dist-info/METADATA
bunnyapi-0.1.5.dist-info/WHEEL
bunnyapi-0.1.5.dist-info/RECORD
