Metadata-Version: 2.1
Name: bunnyapi
Version: 0.1.5
Summary: bunny.net API client
Author: Andy 'danjo' Jacobsen
Author-email: atze.danjo@gmail.com
Requires-Python: >=3.9,<4.0
Classifier: Programming Language :: Python :: 3
Classifier: Programming Language :: Python :: 3.9
Classifier: Programming Language :: Python :: 3.10
Classifier: Programming Language :: Python :: 3.11
Requires-Dist: requests (>=2.25.1,<3.0.0)
